snowfin/__init__.py
snowfin/client.py
snowfin/color.py
snowfin/components.py
snowfin/decorators.py
snowfin/embed.py
snowfin/enums.py
snowfin/errors.py
snowfin/http.py
snowfin/models.py
snowfin/module.py
snowfin/response.py
snowfin-0.1.0.dist-info/LICENSE
snowfin-0.1.0.dist-info/WHEEL
snowfin-0.1.0.dist-info/METADATA
snowfin-0.1.0.dist-info/RECORD
