Metadata-Version: 2.1
Name: snowfin
Version: 0.1.0
Summary: An async discord http interactions framework built on top of Sanic.
License: MIT
Author: kaj
Author-email: 40004347+KAJdev@users.noreply.github.com
Requires-Python: >=3.10,<4.0
Classifier: License :: OSI Approved :: MIT License
Classifier: Programming Language :: Python :: 3
Classifier: Programming Language :: Python :: 3.10
